setup.py
cc_jumpserver/__init__.py
cc_jumpserver/client.py
cc_jumpserver.egg-info/PKG-INFO
cc_jumpserver.egg-info/SOURCES.txt
cc_jumpserver.egg-info/dependency_links.txt
cc_jumpserver.egg-info/not-zip-safe
cc_jumpserver.egg-info/top_level.txt