Metadata-Version: 2.1
Name: cc-jumpserver
Version: 0.0.1
Summary: jumpserver sdk
Home-page: https://github.com/houm01/cc-jumpserver
